sk8plotlib/__init__.py
sk8plotlib/__main__.py
sk8plotlib/camera.py
sk8plotlib/input.py
sk8plotlib/matplotlib_hacks.py
sk8plotlib/physics.py
sk8plotlib/sk8plotlib.py
sk8plotlib/skater.py
sk8plotlib/variables.py
sk8plotlib/maps/__init__.py
sk8plotlib/maps/sinepark.py
sk8plotlib/maps/thebigsine.py
SK8plotlib-0.0.5.dist-info/LICENSE
SK8plotlib-0.0.5.dist-info/METADATA
SK8plotlib-0.0.5.dist-info/WHEEL
SK8plotlib-0.0.5.dist-info/top_level.txt
SK8plotlib-0.0.5.dist-info/RECORD
