Metadata-Version: 2.2
Name: SK8plotlib
Version: 0.0.5
Summary: Turn any matplotlib line chart into a line skateboarding game.
Author-email: Emily Hunt <emily.hunt.physics@gmail.com>
Maintainer-email: Emily Hunt <emily.hunt.physics@gmail.com>
License: MIT License
Project-URL: Homepage, https://github.com/emilyhunt/SK8plotlib
Project-URL: Bug Reports, https://github.com/emilyhunt/SK8plotlib/issues
Project-URL: Source, https://github.com/emilyhunt/SK8plotlib
Keywords: matplotlib
Classifier: Development Status :: 3 - Alpha
Classifier: Intended Audience :: Developers
Classifier: License :: OSI Approved :: MIT License
Classifier: Programming Language :: Python :: 3
Classifier: Programming Language :: Python :: 3.10
Classifier: Programming Language :: Python :: 3.11
Classifier: Programming Language :: Python :: 3.12
Classifier: Programming Language :: Python :: 3 :: Only
Requires-Python: >=3.10
License-File: LICENSE
Requires-Dist: matplotlib
Requires-Dist: ipython
Requires-Dist: pyqt6
Requires-Dist: shapely
Provides-Extra: dev
Requires-Dist: ruff; extra == "dev"
